<?xml version="1.0" encoding="UTF-8"?>
<metadata xml:lang="en"><Esri><CreaDate>20220521</CreaDate><CreaTime>21444000</CreaTime><ArcGISFormat>1.0</ArcGISFormat><SyncOnce>TRUE</SyncOnce><DataProperties><itemProps><itemLocation><linkage Sync="TRUE">file://\\FJB38\Users\usuario\Documents\ArcGIS\ESP_adm\ESP_adm1</linkage><protocol Sync="TRUE">Local Area Network</protocol></itemLocation></itemProps><copyHistory><copy source="C:\Users\usuario\Documents\ArcGIS_Workshop\Data\Shapefiles\ESP_adm1" dest="\\FJB38\Users\usuario\Documents\ArcGIS\ESP_adm\ESP_adm1" date="20170309" time="14480500"></copy></copyHistory></DataProperties></Esri></metadata>
